djrtime/ping.py
djrtime/middlewares.py
djrtime/wsgi.py
djrtime/wrappers.py
djrtime/__init__.py
djrtime/handlers.py
djrtime/conf/global_settings.py
djrtime/conf/__init__.py
djrtime-0.1.0a2.dist-info/top_level.txt
djrtime-0.1.0a2.dist-info/metadata.json
djrtime-0.1.0a2.dist-info/METADATA
djrtime-0.1.0a2.dist-info/WHEEL
djrtime-0.1.0a2.dist-info/RECORD
djrtime-0.1.0a2.dist-info/DESCRIPTION.rst
