Metadata-Version: 2.0
Name: djrtime
Version: 0.1.0a2
Summary: UNKNOWN
Home-page: UNKNOWN
Author: Vinay Karanam
Author-email: UNKNOWN
License: UNKNOWN
Platform: UNKNOWN
Requires-Dist: python-snappy (==0.5)
Requires-Dist: rtime (==0.1.0a2)
